corkit/__init__.py
corkit/cli.py
corkit/dataset.py
corkit/lasco.py
corkit/reconstruction.py
corkit/secchi.py
corkit/utils.py
tests/__init__.py
tests/test_corkit.py
corkit-1.0.16.dist-info/LICENSE
corkit-1.0.16.dist-info/METADATA
corkit-1.0.16.dist-info/WHEEL
corkit-1.0.16.dist-info/entry_points.txt
corkit-1.0.16.dist-info/top_level.txt
corkit-1.0.16.dist-info/RECORD
