Metadata-Version: 2.1
Name: corkit
Version: 1.0.16
Summary: Open source coronagraph data downloader and calibrator
Home-page: https://github.com/Jorgedavyd/corkit
Author: Jorge David Enciso Martínez
Author-email: jorged.encyso@gmail.com
License: MIT
Classifier: Development Status :: 4 - Beta
Classifier: Intended Audience :: Science/Research
Classifier: Intended Audience :: Developers
Classifier: License :: OSI Approved :: MIT License
Classifier: Programming Language :: Python
Classifier: Programming Language :: Python :: 3
Classifier: Programming Language :: Python :: 3.10
Classifier: Programming Language :: Python :: 3.11
Classifier: Programming Language :: Python :: 3.12
Classifier: Programming Language :: Python :: Implementation :: CPython
Classifier: Programming Language :: Python :: Implementation :: PyPy
Classifier: Operating System :: Microsoft :: Windows
Classifier: Operating System :: POSIX :: Linux
Classifier: Operating System :: MacOS :: MacOS X
Classifier: Topic :: Scientific/Engineering
Classifier: Topic :: Scientific/Engineering :: Astronomy
Classifier: Topic :: Scientific/Engineering :: Physics
Classifier: Topic :: Scientific/Engineering :: Mathematics
Classifier: Topic :: Scientific/Engineering :: Visualization
Classifier: Topic :: Scientific/Engineering :: Image Processing
Classifier: Topic :: Scientific/Engineering :: Information Analysis
Classifier: Topic :: Scientific/Engineering :: Artificial Intelligence
Classifier: Topic :: Software Development :: Libraries :: Python Modules
Classifier: Framework :: Matplotlib
Classifier: Framework :: Pytest
Classifier: Framework :: Sphinx
Classifier: Framework :: Jupyter
Classifier: Framework :: IPython
Classifier: Environment :: Console
Classifier: Environment :: Web Environment
Classifier: Natural Language :: English
Classifier: Typing :: Typed
License-File: LICENSE
Requires-Dist: astropy
Requires-Dist: numpy
Requires-Dist: aiofiles
Requires-Dist: scipy
Requires-Dist: aiohttp
Requires-Dist: scikit-image
Requires-Dist: beautifulsoup4
Requires-Dist: matplotlib
Requires-Dist: pillow
Requires-Dist: pandas
Requires-Dist: torch
Requires-Dist: torchvision
Requires-Dist: gdown
